zzero/__init__.py
zzero/client.py
zzero/const.py
zzero/exceptions.py
zzero/server.py
zzero/util.py
zzero-0.1.3.dist-info/METADATA
zzero-0.1.3.dist-info/WHEEL
zzero-0.1.3.dist-info/entry_points.txt
zzero-0.1.3.dist-info/top_level.txt
zzero-0.1.3.dist-info/RECORD
