Metadata-Version: 2.4
Name: zzero
Version: 0.1.3
Summary: Add your description here
Requires-Python: >=3.12
Requires-Dist: dotenv>=0.9.9
Requires-Dist: mcp>=1.9.3
Requires-Dist: requests>=2.32.4
